core/Quantized.py
core/__init__.py
core/utils.py
AdapterLoRa-2.0.0.dist-info/LICENSE
AdapterLoRa-2.0.0.dist-info/METADATA
AdapterLoRa-2.0.0.dist-info/WHEEL
AdapterLoRa-2.0.0.dist-info/top_level.txt
AdapterLoRa-2.0.0.dist-info/RECORD
