Metadata-Version: 2.1
Name: AdapterLoRa
Version: 2.0.0
Summary: A Tool for adaptation Larger Transfomer-Based model and Quantization built top on libraries LoRa and LoRa-Torch.
Home-page: https://github.com/youness-elbrag/AdapterLoRa/
Author: Youness EL BRAG
Author-email: younsselbrag@gmail.com
License: UNKNOWN
Keywords: Quantization,AdapterLLM,PEFT
Platform: UNKNOWN
Classifier: Development Status :: 4 - Beta
Classifier: Intended Audience :: Developers
Classifier: Topic :: Software Development :: Build Tools
Classifier: License :: OSI Approved :: MIT License
Classifier: Programming Language :: Python :: 3.7
Classifier: Programming Language :: Python :: 3.8
Classifier: Programming Language :: Python :: 3.9
Classifier: Programming Language :: Python :: 3.10
Requires-Python: >=3.7
License-File: LICENSE
Requires-Dist: loralib
